svgreplicate/__init__.py
svgreplicate/__main__.py
svgreplicate/svghandler.py
svgreplicate-0.1.1.dist-info/entry_points.txt
svgreplicate-0.1.1.dist-info/WHEEL
svgreplicate-0.1.1.dist-info/METADATA
svgreplicate-0.1.1.dist-info/RECORD
