Metadata-Version: 2.1
Name: svgreplicate
Version: 0.1.1
Summary: Tool for batch modifying and replicating SVG-files
Home-page: https://github.com/janheindejong/svgreplicate
Author: Jan Hein de Jong
Author-email: janhein.dejong@gmail.com
Requires-Python: >=3.9,<4.0
Classifier: Programming Language :: Python :: 3
Classifier: Programming Language :: Python :: 3.10
Classifier: Programming Language :: Python :: 3.9
Project-URL: Repository, https://github.com/janheindejong/svgreplicate
